fileshare/FileShare.py
fileshare/__init__.py
fileshare/utils/Timer.py
fileshare/utils/__init__.py
pyfileshare-1.0.0.dist-info/METADATA
pyfileshare-1.0.0.dist-info/WHEEL
pyfileshare-1.0.0.dist-info/top_level.txt
pyfileshare-1.0.0.dist-info/RECORD
