Metadata-Version: 2.1
Name: pyfileshare
Version: 1.0.0
Summary: PyFileShare is a Python library designed for seamless interaction with the file-sharing service.
Home-page: https://github.com/RedPiarOfficial/FileShare/
Author: RedPiar
Author-email: Regeonwix@gmail.com
License: MIT
Keywords: file sharing,file upload,file download,cloudscraper,BeautifulSoup
Classifier: Programming Language :: Python :: 3
Classifier: License :: OSI Approved :: MIT License
Classifier: Operating System :: OS Independent
Requires-Python: >=3.8
Requires-Dist: cloudscraper
Requires-Dist: bs4
